pytestgen/__init__.py
pytestgen/generator.py
pytestgen/load.py
pytestgen/output.py
pytestgen/parse.py
pytestgen/cli/__init__.py
pytestgen/cli/pytestgen.py
pytestgen-0.1.1.dist-info/LICENSE
pytestgen-0.1.1.dist-info/METADATA
pytestgen-0.1.1.dist-info/WHEEL
pytestgen-0.1.1.dist-info/entry_points.txt
pytestgen-0.1.1.dist-info/top_level.txt
pytestgen-0.1.1.dist-info/RECORD
