Metadata-Version: 2.1
Name: pytestgen
Version: 0.1.1
Summary: Generate pytest tests from your Python source files.
Home-page: https://github.com/Figglewatts/pytestgen
Author: Figglewatts
License: UNKNOWN
Keywords: testing test generation pytest
Platform: UNKNOWN
Classifier: Programming Language :: Python :: 3.7
Classifier: License :: OSI Approved :: MIT License
Classifier: Development Status :: 3 - Alpha
Classifier: Intended Audience :: Developers
Classifier: Operating System :: OS Independent
Classifier: Topic :: Software Development :: Code Generators
Classifier: Topic :: Software Development :: Testing
Requires-Python: >=3.7
Requires-Dist: click (==7.0)
Requires-Dist: jinja2 (==2.11.0)
Requires-Dist: markupsafe (==1.1.1)
